Workbook

Sheet Dashboard
A1: Trane Technologies Financial Review Dashboard
A4: 2025 Revenue | D4: 2025 Gross Margin | G4: 2025 Operating Margin | J4: 2025 Net Margin
A5: ='Financials Data'!B4 -> 21321.9 | D5: ='Financials Data'!G4 -> 0.36160943 | G5: ='Financials Data'!I4 -> 0.1860716 | J5: ='Financials Data'!K4 -> 0.13688274
A7: 2025 Net Earnings | D7: 2025 Operating Cash Flow | G7: Diluted EPS | J7: Debt Ratio
A8: ='Financials Data'!J4 -> 2918.6 | D8: ='Financials Data'!L4 -> 3194.5 | G8: ='Financials Data'!P4 -> 12.98 | J8: ='2025 Ratios'!B9 -> 0.59847717
A10: Key Observations
A11: • Revenue increased each year from 2023 through 2025.
A12: • Gross, operating, and net margins all improved over the three-year period.
A13: • Operating cash flow remained positive in all three years.
A14: • The ratio sheet shows strong interest coverage and times-interest-earned in 2025.
A16: Year | B16: Revenue | C16: Net Earnings | D16: Operating Cash Flow | F16: Ratio | G16: Value
A17: 2023 | B17: 17677.6 | C17: 2023.9 | D17: 2389.6 | F17: Current Ratio | G17: 1.2507357
A18: 2024 | B18: 19838.2 | C18: 2567.9 | D18: 3145.6 | F18: Debt Ratio | G18: 0.59847717
A19: 2025 | B19: 21321.9 | C19: 2918.6 | D19: 3194.5 | F19: Interest Coverage | G19: 19.160565
F20: Times Interest Earned | G20: 17.500662
F21: Return on Assets | G21: 0.13625138
F22: Return on Equity | G22: 0.34019489

Sheet Financials Data
A1: Year | B1: Revenue | C1: Product Revenue | D1: Service Revenue | E1: COGS | F1: Gross Profit | G1: Gross Margin | H1: Operating Income | I1: Operating Margin | J1: Net Earnings Attributable | K1: Net Margin | L1: Operating Cash Flow | M1: Investing Cash Flow | N1: Financing Cash Flow | O1: Basic EPS | P1: Diluted EPS
A2: 2023 | B2: 17677.6 | C2: 11975.4 | D2: 5702.2 | E2: 11820.4 | F2: 5857.2 | G2: 0.33133457 | H2: 2894 | I2: 0.16371001 | J2: 2023.9 | K2: 0.11448952 | L2: 2389.6 | M2: -1172.2 | N2: -1350.3 | O2: 8.85 | P2: 8.77
A3: 2024 | B3: 19838.2 | C3: 13314.5 | D3: 6523.7 | E3: 12757.7 | F3: 7080.5 | G3: 0.35691242 | H3: 3500.1 | I3: 0.17643234 | J3: 2567.9 | K3: 0.12944219 | L3: 3145.6 | M3: -562.9 | N3: -2020.6 | O3: 11.35 | P3: 11.24
A4: 2025 | B4: 21321.9 | C4: 13982.3 | D4: 7339.6 | E4: 13611.7 | F4: 7710.2 | G4: 0.36160943 | H4: 3967.4 | I4: 0.1860716 | J4: 2918.6 | K4: 0.13688274 | L4: 3194.5 | M4: -640 | N4: -2495.8 | O4: 13.09 | P4: 12.98

Sheet Financial Pivot
A1: Trane Technologies Financial Summary Pivot
A3: Metric | B3: Category | C3: 2023 | D3: 2024 | E3: 2025 | F3: 2025 vs 2023 | G3: CAGR / Change
A4: Revenue | B4: Income Statement | C4: 17677.6 | D4: 19838.2 | E4: 21321.9 | F4: =IFERROR((E4-C4)/ABS(C4),"") -> 0.20615355 | G4: =IFERROR((E4/C4)^(1/2)-1,"") -> 0.098250222
A5: Product Revenue | B5: Income Statement | C5: 11975.4 | D5: 13314.5 | E5: 13982.3 | F5: =IFERROR((E5-C5)/ABS(C5),"") -> 0.16758522 | G5: =IFERROR((E5/C5)^(1/2)-1,"") -> 0.080548572
A6: Service Revenue | B6: Income Statement | C6: 5702.2 | D6: 6523.7 | E6: 7339.6 | F6: =IFERROR((E6-C6)/ABS(C6),"") -> 0.28715233 | G6: =IFERROR((E6/C6)^(1/2)-1,"") -> 0.13452736
A7: COGS | B7: Income Statement | C7: 11820.4 | D7: 12757.7 | E7: 13611.7 | F7: =IFERROR((E7-C7)/ABS(C7),"") -> 0.15154309 | G7: =IFERROR((E7/C7)^(1/2)-1,"") -> 0.07309976
A8: Gross Profit | B8: Income Statement | C8: 5857.2 | D8: 7080.5 | E8: 7710.2 | F8: =IFERROR((E8-C8)/ABS(C8),"") -> 0.31636277 | G8: =IFERROR((E8/C8)^(1/2)-1,"") -> 0.14732854
A9: Operating Income | B9: Income Statement | C9: 2894 | D9: 3500.1 | E9: 3967.4 | F9: =IFERROR((E9-C9)/ABS(C9),"") -> 0.37090532 | G9: =IFERROR((E9/C9)^(1/2)-1,"") -> 0.17085666
A10: Net Earnings Attributable | B10: Income Statement | C10: 2023.9 | D10: 2567.9 | E10: 2918.6 | F10: =IFERROR((E10-C10)/ABS(C10),"") -> 0.4420673 | G10: =IFERROR((E10/C10)^(1/2)-1,"") -> 0.20086106
A11: Operating Cash Flow | B11: Cash Flow | C11: 2389.6 | D11: 3145.6 | E11: 3194.5 | F11: =IFERROR((E11-C11)/ABS(C11),"") -> 0.33683462 | G11: =IFERROR((E11/C11)^(1/2)-1,"") -> 0.15621564
A12: Investing Cash Flow | B12: Cash Flow | C12: -1172.2 | D12: -562.9 | E12: -640 | F12: =IFERROR((E12-C12)/ABS(C12),"") -> 0.45401809 | G12: =IFERROR((E12/C12)^(1/2)-1,"") -> -0.26109411
A13: Financing Cash Flow | B13: Cash Flow | C13: -1350.3 | D13: -2020.6 | E13: -2495.8 | F13: =IFERROR((E13-C13)/ABS(C13),"") -> -0.84833 | G13: =IFERROR((E13/C13)^(1/2)-1,"") -> 0.35953301
A14: Basic EPS | B14: Per Share | C14: 8.85 | D14: 11.35 | E14: 13.09 | F14: =IFERROR((E14-C14)/ABS(C14),"") -> 0.47909605 | G14: =IFERROR((E14/C14)^(1/2)-1,"") -> 0.21618093
A15: Diluted EPS | B15: Per Share | C15: 8.77 | D15: 11.24 | E15: 12.98 | F15: =IFERROR((E15-C15)/ABS(C15),"") -> 0.48004561 | G15: =IFERROR((E15/C15)^(1/2)-1,"") -> 0.21657125
A16: Gross Margin | B16: Margin | C16: 0.33133457 | D16: 0.35691242 | E16: 0.36160943 | F16: =IFERROR((E16-C16)/ABS(C16),"") -> 0.09137246 | G16: =E16-C16 -> 0.030274855
A17: Operating Margin | B17: Margin | C17: 0.16371001 | D17: 0.17643234 | E17: 0.1860716 | F17: =IFERROR((E17-C17)/ABS(C17),"") -> 0.1365927 | G17: =E17-C17 -> 0.022361592
A18: Net Margin | B18: Margin | C18: 0.11448952 | D18: 0.12944219 | E18: 0.13688274 | F18: =IFERROR((E18-C18)/ABS(C18),"") -> 0.1955918 | G18: =E18-C18 -> 0.022393212

Sheet 2025 Ratios
A1: Metric | B1: Value | C1: Display | D1: Formula | E1: Interpretation | F1: Category | H1: Ratio Summary by Category
A2: Current Ratio | B2: 1.2507357 | C2: 1.25 | D2: Current assets / current liabilities | E2: Above 1.0, so short-term coverage is positive. | F2: Liquidity / Working Capital | H2: Category | I2: Metric Count | J2: Average Raw Value
A3: Quick Ratio | B3: 0.91612452 | C3: 0.92 | D3: (Current assets - inventory) / current liabilities | E3: Slightly below 1.0, showing inventory still matters to liquidity. | F3: Liquidity / Working Capital | H3: Liquidity / Working Capital | I3: 4 | J3: 16.005293
A4: Inventory Turnover | B4: 6.4706693 | C4: 6.47 | D4: COGS / inventory | E4: About two months of inventory on hand. | F4: Liquidity / Working Capital | H4: Profitability | I4: 5 | J4: 5.3509128
A5: Days Sales Outstanding | B5: 55.383643 | C5: 55.4 days | D5: Accounts receivable / average revenue per day | E5: About 55 days, reasonable for 60-day terms but high for 30-day terms. | F5: Liquidity / Working Capital | H5: Leverage / Coverage | I5: 4 | J5: 9.688498
A6: Gross Margin | B6: 0.36160943 | C6: 36.2% | D6: Gross profit / revenue | E6: Improved to 36.2 percent in 2025. | F6: Profitability | H6: Returns | I6: 2 | J6: 0.23822314
A7: Operating Margin | B7: 0.1860716 | C7: 18.6% | D7: Operating income / revenue | E7: Operating leverage is strong at 18.6 percent. | F7: Profitability
A8: Net Margin | B8: 0.13688274 | C8: 13.7% | D8: Net earnings attributable / revenue | E8: Healthy bottom-line margin at 13.7 percent. | F8: Profitability
A9: Debt Ratio | B9: 0.59847717 | C9: 59.8% | D9: Total liabilities / total assets | E9: Liabilities are about 59.8 percent of assets. | F9: Leverage / Coverage
A10: Debt-to-Equity Ratio | B10: 1.4942885 | C10: 1.49 | D10: Total liabilities / shareholders' equity | E10: Above 1.0, so leverage should be watched. | F10: Leverage / Coverage
A11: Interest Coverage | B11: 19.160565 | C11: 19.16 | D11: EBITDA / interest expense | E11: Very strong coverage of interest expense. | F11: Leverage / Coverage
A12: Times Interest Earned | B12: 17.500662 | C12: 17.5 | D12: EBIT / interest expense | E12: Also very strong. | F12: Leverage / Coverage
A13: Return on Assets | B13: 0.13625138 | C13: 13.6% | D13: Net earnings attributable / total assets | E13: Strong asset return for an industrial company. | F13: Returns
A14: Return on Equity | B14: 0.34019489 | C14: 34.0% | D14: Net earnings attributable / shareholders' equity | E14: Very strong return to shareholders. | F14: Returns
A15: Basic EPS | B15: 13.09 | C15: $13.09 | D15: Annual report EPS | E15: Up from $11.35 in 2024. | F15: Profitability
A16: Diluted EPS | B16: 12.98 | C16: $12.98 | D16: Annual report EPS | E16: Up from $11.24 in 2024. | F16: Profitability
